alu.vhd
-- simple template

library ieee;
use ieee.std_logic_1164.all;
use ieee.numeric_std.all;

entity alu is
  port 
  (
    d      : in unsigned  (3 downto 0) ;
    e      : in unsigned  (3 downto 0) ;
    f      : in std_logic_vector (1 downto 0) ;
    q      : out unsigned (4 downto 0) 
  );

end entity;

architecture rtl of alu is

begin
  -- assignments and processes go here
  process (d , e , f) is 
  begin
	 case f is 
		when "00" =>
			q <= ('0' & d) + ('0' & e);
		when "01" =>
			q <= ('0' & (d - e));
		when "10" =>
			q <= ('0' & (d and e));
		when others =>
			q <= ('0' & (d or e));
	 end case;
  end process;
end architecture;

calc.vhd
-- simple template

library ieee;
use ieee.std_logic_1164.all;
use ieee.numeric_std.all;

entity calc is
  port 
  (
    a      : in unsigned  (3 downto 0);
    b      : in unsigned  (3 downto 0);
    c      : in std_logic_vector (1 downto 0);
    result : out unsigned (4 downto 0)
  );

end entity;

architecture rtl of calc is
  -- definitions go here
  component alu
		port(
			 d      : in unsigned  (3 downto 0);
			 e      : in unsigned  (3 downto 0);
			 f      : in std_logic_vector (1 downto 0);
			 q      : out unsigned (4 downto 0)
		);
  end component;
begin
  -- assignments and processes go here
  alu1: alu
    port map( d => a, e => b, f => c, q => result);

end rtl;

calcbench.vhd
-- Bruce A. Maxwell, edited by Stephanie Taylor
-- Spring 2013
-- CS 232
--
-- Test bench program for calc.vhd and alu.vhd.  Creates a
-- series of signals for the two inputs and the function to
-- apply to them

library ieee;
use ieee.std_logic_1164.all;
use ieee.numeric_std.all;

entity calcbench is
end entity;

architecture test of calcbench is
	
  -- internal signals to drive the circuit
  signal bench_a : unsigned (3 downto 0);
  signal bench_b : unsigned (3 downto 0);
  signal bench_c : std_logic_vector( 1 downto 0 );
  signal bench_f : unsigned(4 downto 0);

  -- component we want to test
  component calc
  port 
  (
    a      : in unsigned  (3 downto 0);
    b      : in unsigned  (3 downto 0);
    c      : in std_logic_vector (1 downto 0);
    result : out unsigned (4 downto 0)
  );
  end component;
  

begin
  -- set the inputs a, b, c to test various combinations
  bench_a <= "0000", "0001" after 20 ns, "0010" after 40 ns, "0111" after 60 ns;
  bench_b <= "0000", "0001" after 10 ns, "0010" after 30 ns, "0100" after 50 ns;
  bench_c <= "00", "01" after 15 ns, "00"after 25 ns, "01" after 45 ns,
     "10" after 50 ns, "11" after 65 ns, "00" after 70 ns;

  -- port map the calc circuit and connect the drivers and output signal
  c1: calc port map ( bench_a, bench_b, bench_c, result => bench_f );

end test;

calcbench.vcd
$date
  Tue Mar 11 14:50:09 2025
$end
$version
  GHDL v0
$end
$timescale
  1 fs
$end
$scope module standard $end
$upscope $end
$scope module std_logic_1164 $end
$upscope $end
$scope module numeric_std $end
$upscope $end
$scope module calcbench $end
$var reg 4 ! bench_a[3:0] $end
$var reg 4 " bench_b[3:0] $end
$var reg 2 # bench_c[1:0] $end
$var reg 5 $ bench_f[4:0] $end
$scope module c1 $end
$var reg 4 % a[3:0] $end
$var reg 4 & b[3:0] $end
$var reg 2 ' c[1:0] $end
$var reg 5 ( result[4:0] $end
$scope module alu1 $end
$var reg 4 ) d[3:0] $end
$var reg 4 * e[3:0] $end
$var reg 2 + f[1:0] $end
$var reg 5 , q[4:0] $end
$upscope $end
$upscope $end
$upscope $end
$enddefinitions $end
#0
b0000 !
b0000 "
b00 #
b00000 $
b0000 %
b0000 &
b00 '
b00000 (
b0000 )
b0000 *
b00 +
b00000 ,
#10000000
b0001 "
b00001 $
b0001 &
b00001 (
b0001 *
b00001 ,
#15000000
b01 #
b01111 $
b01 '
b01111 (
b01 +
b01111 ,
#20000000
b0001 !
b00000 $
b0001 %
b00000 (
b0001 )
b00000 ,
#25000000
b00 #
b00010 $
b00 '
b00010 (
b00 +
b00010 ,
#30000000
b0010 "
b00011 $
b0010 &
b00011 (
b0010 *
b00011 ,
#40000000
b0010 !
b00100 $
b0010 %
b00100 (
b0010 )
b00100 ,
#45000000
b01 #
b00000 $
b01 '
b00000 (
b01 +
b00000 ,
#50000000
b0100 "
b10 #
b0100 &
b10 '
b0100 *
b10 +
#60000000
b0111 !
b00100 $
b0111 %
b00100 (
b0111 )
b00100 ,
#65000000
b11 #
b00111 $
b11 '
b00111 (
b11 +
b00111 ,
#70000000
b00 #
b01011 $
b00 '
b01011 (
b00 +
b01011 ,
