extensionrom.vhd
-- Quartus II VHDL Template
-- Unsigned Adder

library ieee;
use ieee.std_logic_1164.all;
use ieee.numeric_std.all;

entity extensionrom is
    port (
        addr : in  std_logic_vector(5 downto 0);
        data : out std_logic_vector(2 downto 0)
    );
end entity;

architecture rtl of extensionrom is
begin
    data <= 
        "000" when addr = "000000" else -- move 0s to LR  00000000
        "101" when addr = "000001" else -- bit invert LR  11111111
        "101" when addr = "000010" else -- bit invert LR  00000000
        "101" when addr = "000011" else -- bit invert LR  11111111
        "001" when addr = "000100" else -- shift LR right 01111111
        "001" when addr = "000101" else -- shift LR right 00111111
        "001" when addr = "000110" else -- rotate LR left 01111110
        "111" when addr = "000111" else -- rotate LR left 11111100
        "111" when addr = "001001" else -- rotate LR left 11111001
        "111" when addr = "001010" else -- rotate LR left 11110011
        "010" when addr = "001011" else -- shift LR left  11100110
        "111" when addr = "001100" else -- shift LR left  11001100
        "111" when addr = "001101" else -- add 1 to LR    11001101
        "101" when addr = "001110" else -- sub 1 from LR  11001100
        "000" when addr = "001111" else -- bit invert LR  00110011
        "101" when addr = "010000" else -- BRZ (Branch if Zero)
        "001" when addr = "010001" else -- move 0s to LR  00000000
        "001" when addr = "010010" else -- bit invert LR  11111111
        "011" when addr = "010011" else -- bit invert LR  00000000
        "011" when addr = "010100" else -- bit invert LR  11111111
        "011" when addr = "010101" else -- shift LR right 01111111
        "010" when addr = "010110" else -- shift LR right 00111111
        "010" when addr = "010111" else -- rotate LR left 01111110
        "010" when addr = "011000" else -- rotate LR left 11111100
        "101" when addr = "011001" else -- rotate LR left 11111001
        "101" when addr = "011010" else -- rotate LR left 11110011
        "010" when addr = "011011" else -- shift LR left  11100110
        "010" when addr = "011100" else -- shift LR left  11001100
        "011" when addr = "011101" else -- add 1 to LR    11001101
        "100" when addr = "011110" else -- sub 1 from LR  11001100
        "101" when addr = "011111" else -- bit invert LR  00110011
        "110" when addr = "100000" else -- BRZ (Branch if Zero)
        "111" when addr = "100001" else -- rotate LR left 11110011
        "010" when addr = "100010" else -- shift LR left  11100110
        "010" when addr = "100011" else -- shift LR left  11001100
        "011" when addr = "100100" else -- add 1 to LR    11001101
        "100" when addr = "100101" else -- sub 1 from LR  11001100
        "101" when addr = "100110" else -- bit invert LR  00110011
        "110" when addr = "100111" else -- BRZ (Branch if Zero)
        "010" when addr = "101000" else -- shift LR left  11001100
        "000" when addr = "101001" else -- add 1 to LR    11001101
        "101" when addr = "101010" else -- sub 1 from LR  11001100
        "010" when addr = "101011" else -- bit invert LR  00110011
        "110" when addr = "101100" else -- BRZ (Branch if Zero)
        "011" when addr = "101101" else -- sub 1 from LR  11001100
        "010" when addr = "101110" else -- bit invert LR  00110011
        "110" when addr = "101111" else -- BRZ (Branch if Zero)
        "101" when addr = "110000" else -- shift LR left  11001100
        "011" when addr = "110001" else -- add 1 to LR    11001101
        "010" when addr = "110010" else -- sub 1 from LR  11001100
        "110" when addr = "110011" else -- bit invert LR  00110011
        "110" when addr = "110100" else -- BRZ (Branch if Zero)
        "100" when addr = "110101" else -- sub 1 from LR  11001100
        "101" when addr = "110110" else -- bit invert LR  00110011
        "110" when addr = "110111" else -- BRZ (Branch if Zero)
        "000" when addr = "111000" else -- shift LR left  11001100
        "101" when addr = "111001" else -- add 1 to LR    11001101
        "000" when addr = "111010" else -- sub 1 from LR  11001100
        "101" when addr = "111011" else -- bit invert LR  00110011
        "110" when addr = "111100" else -- BRZ (Branch if Zero)
        "011";                        -- add 1 to LR    00110100
end rtl;

extension.vhd
-- Quartus II VHDL Template
-- Four-State Moore State Machine

-- A Moore machine's outputs are dependent only on the current state.
-- The output is written only when the state changes.  (State
-- transitions are synchronous.)

library ieee;
use ieee.std_logic_1164.all;
use ieee.numeric_std.all;  -- defines the unsigned type

entity extension is

	port(
		clk		 : in	std_logic;
		reset	    : in	std_logic;
		speed_button: in  std_logic;  -- New speed control button
		speed_button_4x: in std_logic;
		lightsig	 : out	std_logic_vector(7 downto 0);  -- output signal that will drive the LED display on the board
		IRView	 : out	std_logic_vector(2 downto 0);  -- IR and PC will let you monitor the values of the IR and PC registers.
		PCView    : out unsigned (5 downto 0)
	);

end entity;

architecture rtl of extension is

	component extensionrom
		port(
			addr	 : in std_logic_vector (5 downto 0);
			data   : out std_logic_vector(2 downto 0)
		);
	end component;


	type state_type is (sFetch, sExecute);
	signal IR  : std_logic_vector(2 downto 0);
	signal PC  : unsigned(5 downto 0);
	signal LR  : unsigned (7 downto 0);
	signal ROMvalue  : std_logic_vector(2 downto 0);
	signal state   : state_type;
	signal clk_enable : std_logic; 
   signal clk_counter : integer := 0;  

begin


    process(clk, reset)
    begin
        if reset = '0' then
            clk_enable <= '0';
            clk_counter <= 0;
        elsif rising_edge(clk) then
            if speed_button_4x = '1' then
                clk_enable <= '1';
                clk_counter <= 0;
            elsif speed_button = '1' then
                if clk_counter = 1 then
                    clk_enable <= '1';
                    clk_counter <= 0;
                else
                    clk_enable <= '0';
                    clk_counter <= clk_counter + 1;
                end if;
            else
                if clk_counter = 3 then
                    clk_enable <= '1';
                    clk_counter <= 0;
                else
                    clk_enable <= '0';
                    clk_counter <= clk_counter + 1;
                end if;
            end if;
        end if;
    end process;

    process(clk, reset)
    begin
        if reset = '0' then
            state <= sFetch;
            IR <= "000";
            PC <= "000000";
            LR <= "00000000";
        elsif rising_edge(clk) and clk_enable = '1' then
            case state is
                when sFetch =>
                    IR <= ROMvalue;
                    PC <= PC + 1;
                    state <= sExecute;
                when sExecute =>
                    case IR is
                        when "000" =>  
                            LR <= "00000000";
                        when "001" =>  
                            LR <= '0' & LR(7 downto 1);
                        when "010" =>  
                            LR <= LR(6 downto 0) & '0';
                        when "011" => 
                            LR <= LR + 1;
                        when "100" =>  
                            LR <= LR - 1;
                        when "101" =>  
                            LR <= not LR;
                        when "110" =>  
                            if LR = "00000000" then
                                PC <= unsigned("000" & ROMvalue);  
                            end if;
                        when "111" =>  
                            PC <= unsigned("000" & ROMvalue);  
                        when others =>
                            LR <= (others => '0');
                    end case;
                    state <= sFetch;
            end case;
        end if;
    end process;

	-- Output depends solely on the current state
	
	lightsig <= std_logic_vector(LR);
	IRView <= IR;
	PCView <= PC;
	
	extensionrom1 : extensionrom
		port map ( 
			addr => std_logic_vector(PC), 
			data => ROMValue
		);


	
end rtl;

extensionbench.vhd
-- Bruce A. Maxwell/Stephanie Taylor
-- Fall 2023
-- CS 232
--
-- test program for the lights circuit
--

library ieee;
use ieee.std_logic_1164.all;
use ieee.numeric_std.all;

entity extensionbench is
end entity;

architecture test of extensionbench is
  constant num_cycles : integer := 160;
  signal clk : std_logic := '1';
  signal reset : std_logic;
  signal speed_button : std_logic := '0';
  signal speed_button_4x : std_logic := '0';
  component extension
    port( clk, reset : in std_logic;
			 speed_button: in std_logic;
			 speed_button_4x : in std_logic;
          lightsig   : out std_logic_vector(7 downto 0) );
  end component;
  signal lightsig : std_logic_vector(7 downto 0);
begin
  reset <= '0', '1' after 5 ns;
  process begin
    for i in 1 to num_cycles loop
      clk <= not clk;
      wait for 5 ns;
      clk <= not clk;
      wait for 5 ns;
    end loop;
    wait;
  end process;
  process begin
        wait for 25 ns;
		  speed_button_4x <= '1'; 
        wait for 200 ns;
        speed_button_4x <= '0';  
        wait for 100 ns;
        speed_button <= '1'; 
        wait for 200 ns;
		  speed_button <= '0';
		  wait for 300 ns;
		  speed_button_4x <= '1';
		  wait for 500 ns;
		  speed_button_4x <= '0';
        wait;
    end process;
  L0: extension port map( clk, reset, speed_button, speed_button_4x, lightsig );
end test;

extensionbench.vcd
$date
  Fri Mar 21 16:19:43 2025
$end
$version
  GHDL v0
$end
$timescale
  1 fs
$end
$scope module standard $end
$upscope $end
$scope module std_logic_1164 $end
$upscope $end
$scope module numeric_std $end
$upscope $end
$scope module extensionbench $end
$var reg 1 ! clk $end
$var reg 1 " reset $end
$var reg 1 # speed_button $end
$var reg 1 $ speed_button_4x $end
$var reg 8 % lightsig[7:0] $end
$scope module l0 $end
$var reg 1 & clk $end
$var reg 1 ' reset $end
$var reg 1 ( speed_button $end
$var reg 1 ) speed_button_4x $end
$var reg 8 * lightsig[7:0] $end
$var reg 3 + irview[2:0] $end
$var reg 6 , pcview[5:0] $end
$var reg 3 - ir[2:0] $end
$var reg 6 . pc[5:0] $end
$var reg 8 / lr[7:0] $end
$var reg 3 0 romvalue[2:0] $end
$comment state is not handled $end
$var reg 1 1 clk_enable $end
$var integer 32 2 clk_counter $end
$scope module extensionrom1 $end
$var reg 6 3 addr[5:0] $end
$var reg 3 4 data[2:0] $end
$upscope $end
$upscope $end
$upscope $end
$enddefinitions $end
#0
0!
0"
0#
0$
b00000000 %
0&
0'
0(
0)
b00000000 *
b000 +
b000000 ,
b000 -
b000000 .
b00000000 /
b000 0
01
b0 2
b000000 3
b000 4
#5000000
1!
1"
1&
1'
b1 2
#10000000
0!
0&
#15000000
1!
1&
b10 2
#20000000
0!
0&
#25000000
1!
1$
1&
1)
11
b0 2
#30000000
0!
0&
#35000000
1!
1&
b000001 ,
b000001 .
b101 0
b000001 3
b101 4
#40000000
0!
0&
#45000000
1!
1&
#50000000
0!
0&
#55000000
1!
1&
b101 +
b000010 ,
b101 -
b000010 .
b000010 3
#60000000
0!
0&
#65000000
1!
b11111111 %
1&
b11111111 *
b11111111 /
#70000000
0!
0&
#75000000
1!
1&
b000011 ,
b000011 .
b000011 3
#80000000
0!
0&
#85000000
1!
b00000000 %
1&
b00000000 *
b00000000 /
#90000000
0!
0&
#95000000
1!
1&
b000100 ,
b000100 .
b001 0
b000100 3
b001 4
#100000000
0!
0&
#105000000
1!
b11111111 %
1&
b11111111 *
b11111111 /
#110000000
0!
0&
#115000000
1!
1&
b001 +
b000101 ,
b001 -
b000101 .
b000101 3
#120000000
0!
0&
#125000000
1!
b01111111 %
1&
b01111111 *
b01111111 /
#130000000
0!
0&
#135000000
1!
1&
b000110 ,
b000110 .
b000110 3
#140000000
0!
0&
#145000000
1!
b00111111 %
1&
b00111111 *
b00111111 /
#150000000
0!
0&
#155000000
1!
1&
b000111 ,
b000111 .
b111 0
b000111 3
b111 4
#160000000
0!
0&
#165000000
1!
b00011111 %
1&
b00011111 *
b00011111 /
#170000000
0!
0&
#175000000
1!
1&
b111 +
b001000 ,
b111 -
b001000 .
b011 0
b001000 3
b011 4
#180000000
0!
0&
#185000000
1!
1&
b000011 ,
b000011 .
b101 0
b000011 3
b101 4
#190000000
0!
0&
#195000000
1!
1&
b101 +
b000100 ,
b101 -
b000100 .
b001 0
b000100 3
b001 4
#200000000
0!
0&
#205000000
1!
b11100000 %
1&
b11100000 *
b11100000 /
#210000000
0!
0&
#215000000
1!
1&
b001 +
b000101 ,
b001 -
b000101 .
b000101 3
#220000000
0!
0&
#225000000
1!
0$
b01110000 %
1&
0)
b01110000 *
b01110000 /
01
b1 2
#230000000
0!
0&
#235000000
1!
1&
b10 2
#240000000
0!
0&
#245000000
1!
1&
b11 2
#250000000
0!
0&
#255000000
1!
1&
11
b0 2
#260000000
0!
0&
#265000000
1!
1&
b000110 ,
b000110 .
01
b1 2
b000110 3
#270000000
0!
0&
#275000000
1!
1&
b10 2
#280000000
0!
0&
#285000000
1!
1&
b11 2
#290000000
0!
0&
#295000000
1!
1&
11
b0 2
#300000000
0!
0&
#305000000
1!
b00111000 %
1&
b00111000 *
b00111000 /
01
b1 2
#310000000
0!
0&
#315000000
1!
1&
b10 2
#320000000
0!
0&
#325000000
1!
1#
1&
1(
b11 2
#330000000
0!
0&
#335000000
1!
1&
b100 2
#340000000
0!
0&
#345000000
1!
1&
b101 2
#350000000
0!
0&
#355000000
1!
1&
b110 2
#360000000
0!
0&
#365000000
1!
1&
b111 2
#370000000
0!
0&
#375000000
1!
1&
b1000 2
#380000000
0!
0&
#385000000
1!
1&
b1001 2
#390000000
0!
0&
#395000000
1!
1&
b1010 2
#400000000
0!
0&
#405000000
1!
1&
b1011 2
#410000000
0!
0&
#415000000
1!
1&
b1100 2
#420000000
0!
0&
#425000000
1!
1&
b1101 2
#430000000
0!
0&
#435000000
1!
1&
b1110 2
#440000000
0!
0&
#445000000
1!
1&
b1111 2
#450000000
0!
0&
#455000000
1!
1&
b10000 2
#460000000
0!
0&
#465000000
1!
1&
b10001 2
#470000000
0!
0&
#475000000
1!
1&
b10010 2
#480000000
0!
0&
#485000000
1!
1&
b10011 2
#490000000
0!
0&
#495000000
1!
1&
b10100 2
#500000000
0!
0&
#505000000
1!
1&
b10101 2
#510000000
0!
0&
#515000000
1!
1&
b10110 2
#520000000
0!
0&
#525000000
1!
0#
1&
0(
b10111 2
#530000000
0!
0&
#535000000
1!
1&
b11000 2
#540000000
0!
0&
#545000000
1!
1&
b11001 2
#550000000
0!
0&
#555000000
1!
1&
b11010 2
#560000000
0!
0&
#565000000
1!
1&
b11011 2
#570000000
0!
0&
#575000000
1!
1&
b11100 2
#580000000
0!
0&
#585000000
1!
1&
b11101 2
#590000000
0!
0&
#595000000
1!
1&
b11110 2
#600000000
0!
0&
#605000000
1!
1&
b11111 2
#610000000
0!
0&
#615000000
1!
1&
b100000 2
#620000000
0!
0&
#625000000
1!
1&
b100001 2
#630000000
0!
0&
#635000000
1!
1&
b100010 2
#640000000
0!
0&
#645000000
1!
1&
b100011 2
#650000000
0!
0&
#655000000
1!
1&
b100100 2
#660000000
0!
0&
#665000000
1!
1&
b100101 2
#670000000
0!
0&
#675000000
1!
1&
b100110 2
#680000000
0!
0&
#685000000
1!
1&
b100111 2
#690000000
0!
0&
#695000000
1!
1&
b101000 2
#700000000
0!
0&
#705000000
1!
1&
b101001 2
#710000000
0!
0&
#715000000
1!
1&
b101010 2
#720000000
0!
0&
#725000000
1!
1&
b101011 2
#730000000
0!
0&
#735000000
1!
1&
b101100 2
#740000000
0!
0&
#745000000
1!
1&
b101101 2
#750000000
0!
0&
#755000000
1!
1&
b101110 2
#760000000
0!
0&
#765000000
1!
1&
b101111 2
#770000000
0!
0&
#775000000
1!
1&
b110000 2
#780000000
0!
0&
#785000000
1!
1&
b110001 2
#790000000
0!
0&
#795000000
1!
1&
b110010 2
#800000000
0!
0&
#805000000
1!
1&
b110011 2
#810000000
0!
0&
#815000000
1!
1&
b110100 2
#820000000
0!
0&
#825000000
1!
1$
1&
1)
11
b0 2
#830000000
0!
0&
#835000000
1!
1&
b000111 ,
b000111 .
b111 0
b000111 3
b111 4
#840000000
0!
0&
#845000000
1!
b00011100 %
1&
b00011100 *
b00011100 /
#850000000
0!
0&
#855000000
1!
1&
b111 +
b001000 ,
b111 -
b001000 .
b011 0
b001000 3
b011 4
#860000000
0!
0&
#865000000
1!
1&
b000011 ,
b000011 .
b101 0
b000011 3
b101 4
#870000000
0!
0&
#875000000
1!
1&
b101 +
b000100 ,
b101 -
b000100 .
b001 0
b000100 3
b001 4
#880000000
0!
0&
#885000000
1!
b11100011 %
1&
b11100011 *
b11100011 /
#890000000
0!
0&
#895000000
1!
1&
b001 +
b000101 ,
b001 -
b000101 .
b000101 3
#900000000
0!
0&
#905000000
1!
b01110001 %
1&
b01110001 *
b01110001 /
#910000000
0!
0&
#915000000
1!
1&
b000110 ,
b000110 .
b000110 3
#920000000
0!
0&
#925000000
1!
b00111000 %
1&
b00111000 *
b00111000 /
#930000000
0!
0&
#935000000
1!
1&
b000111 ,
b000111 .
b111 0
b000111 3
b111 4
#940000000
0!
0&
#945000000
1!
b00011100 %
1&
b00011100 *
b00011100 /
#950000000
0!
0&
#955000000
1!
1&
b111 +
b001000 ,
b111 -
b001000 .
b011 0
b001000 3
b011 4
#960000000
0!
0&
#965000000
1!
1&
b000011 ,
b000011 .
b101 0
b000011 3
b101 4
#970000000
0!
0&
#975000000
1!
1&
b101 +
b000100 ,
b101 -
b000100 .
b001 0
b000100 3
b001 4
#980000000
0!
0&
#985000000
1!
b11100011 %
1&
b11100011 *
b11100011 /
#990000000
0!
0&
#995000000
1!
1&
b001 +
b000101 ,
b001 -
b000101 .
b000101 3
#1000000000
0!
0&
#1005000000
1!
b01110001 %
1&
b01110001 *
b01110001 /
#1010000000
0!
0&
#1015000000
1!
1&
b000110 ,
b000110 .
b000110 3
#1020000000
0!
0&
#1025000000
1!
b00111000 %
1&
b00111000 *
b00111000 /
#1030000000
0!
0&
#1035000000
1!
1&
b000111 ,
b000111 .
b111 0
b000111 3
b111 4
#1040000000
0!
0&
#1045000000
1!
b00011100 %
1&
b00011100 *
b00011100 /
#1050000000
0!
0&
#1055000000
1!
1&
b111 +
b001000 ,
b111 -
b001000 .
b011 0
b001000 3
b011 4
#1060000000
0!
0&
#1065000000
1!
1&
b000011 ,
b000011 .
b101 0
b000011 3
b101 4
#1070000000
0!
0&
#1075000000
1!
1&
b101 +
b000100 ,
b101 -
b000100 .
b001 0
b000100 3
b001 4
#1080000000
0!
0&
#1085000000
1!
b11100011 %
1&
b11100011 *
b11100011 /
#1090000000
0!
0&
#1095000000
1!
1&
b001 +
b000101 ,
b001 -
b000101 .
b000101 3
#1100000000
0!
0&
#1105000000
1!
b01110001 %
1&
b01110001 *
b01110001 /
#1110000000
0!
0&
#1115000000
1!
1&
b000110 ,
b000110 .
b000110 3
#1120000000
0!
0&
#1125000000
1!
b00111000 %
1&
b00111000 *
b00111000 /
#1130000000
0!
0&
#1135000000
1!
1&
b000111 ,
b000111 .
b111 0
b000111 3
b111 4
#1140000000
0!
0&
#1145000000
1!
b00011100 %
1&
b00011100 *
b00011100 /
#1150000000
0!
0&
#1155000000
1!
1&
b111 +
b001000 ,
b111 -
b001000 .
b011 0
b001000 3
b011 4
#1160000000
0!
0&
#1165000000
1!
1&
b000011 ,
b000011 .
b101 0
b000011 3
b101 4
#1170000000
0!
0&
#1175000000
1!
1&
b101 +
b000100 ,
b101 -
b000100 .
b001 0
b000100 3
b001 4
#1180000000
0!
0&
#1185000000
1!
b11100011 %
1&
b11100011 *
b11100011 /
#1190000000
0!
0&
#1195000000
1!
1&
b001 +
b000101 ,
b001 -
b000101 .
b000101 3
#1200000000
0!
0&
#1205000000
1!
b01110001 %
1&
b01110001 *
b01110001 /
#1210000000
0!
0&
#1215000000
1!
1&
b000110 ,
b000110 .
b000110 3
#1220000000
0!
0&
#1225000000
1!
b00111000 %
1&
b00111000 *
b00111000 /
#1230000000
0!
0&
#1235000000
1!
1&
b000111 ,
b000111 .
b111 0
b000111 3
b111 4
#1240000000
0!
0&
#1245000000
1!
b00011100 %
1&
b00011100 *
b00011100 /
#1250000000
0!
0&
#1255000000
1!
1&
b111 +
b001000 ,
b111 -
b001000 .
b011 0
b001000 3
b011 4
#1260000000
0!
0&
#1265000000
1!
1&
b000011 ,
b000011 .
b101 0
b000011 3
b101 4
#1270000000
0!
0&
#1275000000
1!
1&
b101 +
b000100 ,
b101 -
b000100 .
b001 0
b000100 3
b001 4
#1280000000
0!
0&
#1285000000
1!
b11100011 %
1&
b11100011 *
b11100011 /
#1290000000
0!
0&
#1295000000
1!
1&
b001 +
b000101 ,
b001 -
b000101 .
b000101 3
#1300000000
0!
0&
#1305000000
1!
b01110001 %
1&
b01110001 *
b01110001 /
#1310000000
0!
0&
#1315000000
1!
1&
b000110 ,
b000110 .
b000110 3
#1320000000
0!
0&
#1325000000
1!
0$
b00111000 %
1&
0)
b00111000 *
b00111000 /
01
b1 2
#1330000000
0!
0&
#1335000000
1!
1&
b10 2
#1340000000
0!
0&
#1345000000
1!
1&
b11 2
#1350000000
0!
0&
#1355000000
1!
1&
11
b0 2
#1360000000
0!
0&
#1365000000
1!
1&
b000111 ,
b000111 .
b111 0
01
b1 2
b000111 3
b111 4
#1370000000
0!
0&
#1375000000
1!
1&
b10 2
#1380000000
0!
0&
#1385000000
1!
1&
b11 2
#1390000000
0!
0&
#1395000000
1!
1&
11
b0 2
#1400000000
0!
0&
#1405000000
1!
b00011100 %
1&
b00011100 *
b00011100 /
01
b1 2
#1410000000
0!
0&
#1415000000
1!
1&
b10 2
#1420000000
0!
0&
#1425000000
1!
1&
b11 2
#1430000000
0!
0&
#1435000000
1!
1&
11
b0 2
#1440000000
0!
0&
#1445000000
1!
1&
b111 +
b001000 ,
b111 -
b001000 .
b011 0
01
b1 2
b001000 3
b011 4
#1450000000
0!
0&
#1455000000
1!
1&
b10 2
#1460000000
0!
0&
#1465000000
1!
1&
b11 2
#1470000000
0!
0&
#1475000000
1!
1&
11
b0 2
#1480000000
0!
0&
#1485000000
1!
1&
b000011 ,
b000011 .
b101 0
01
b1 2
b000011 3
b101 4
#1490000000
0!
0&
#1495000000
1!
1&
b10 2
#1500000000
0!
0&
#1505000000
1!
1&
b11 2
#1510000000
0!
0&
#1515000000
1!
1&
11
b0 2
#1520000000
0!
0&
#1525000000
1!
1&
b101 +
b000100 ,
b101 -
b000100 .
b001 0
01
b1 2
b000100 3
b001 4
#1530000000
0!
0&
#1535000000
1!
1&
b10 2
#1540000000
0!
0&
#1545000000
1!
1&
b11 2
#1550000000
0!
0&
#1555000000
1!
1&
11
b0 2
#1560000000
0!
0&
#1565000000
1!
b11100011 %
1&
b11100011 *
b11100011 /
01
b1 2
#1570000000
0!
0&
#1575000000
1!
1&
b10 2
#1580000000
0!
0&
#1585000000
1!
1&
b11 2
#1590000000
0!
0&
#1595000000
1!
1&
11
b0 2
